multi_agent_alpha/__init__.py
multi_agent_alpha-0.1.3.dist-info/LICENSE
multi_agent_alpha-0.1.3.dist-info/METADATA
multi_agent_alpha-0.1.3.dist-info/WHEEL
multi_agent_alpha-0.1.3.dist-info/RECORD
