Metadata-Version: 2.1
Name: multi-agent-alpha
Version: 0.1.3
Summary: Multi-Agent Alpha is a robust, open-source framework for building, managing, and deploying intelligent multi-agent systems. It provides a flexible architecture for creating custom agents, with a focus on code quality, testing, and continuous integration.
License: CC-BY-NC-4.0
Author: Nishchal Gaba
Author-email: nishgaba.ai@gmail.com
Requires-Python: >=3.12,<4.0
Classifier: License :: Other/Proprietary License
Classifier: Programming Language :: Python :: 3
Classifier: Programming Language :: Python :: 3.12
Requires-Dist: fastapi (>=0.112.1,<0.113.0)
Requires-Dist: langchain (>=0.2.14,<0.3.0)
Requires-Dist: numpy (>=1.26.0,<2.0.0)
Requires-Dist: pandas (>=2.2.2,<3.0.0)
Requires-Dist: pydantic (>=2.2.1,<3.0.0)
Requires-Dist: requests (>=2.31.0,<3.0.0)
